{
  "areas": [
    {
      "id": "og",
      "name": "Obergeschoss",
      "grid": {"columns": 5, "rows": 8},
      "tables": [
        {"id": 101, "x": 4, "y": 4}, {"id": 102, "x": 5, "y": 5}, {"id": 103, "x": 5, "y": 3}, {"id": 104, "x": 5, "y": 2},
        {"id": 105, "x": 5, "y": 1}, {"id": 106, "x": 4, "y": 1}, {"id": 107, "x": 3, "y": 2}, {"id": 108, "x": 2, "y": 1}, {"id": 109, "x": 1, "y": 1},
        {"id": 110, "x": 1, "y": 2}, {"id": 111, "x": 1, "y": 3}, {"id": 112, "x": 1, "y": 5}, {"id": 113, "x": 2, "y": 4}, {"id": 114, "x": 1, "y": 6},
	{"id": 115, "x": 1, "y": 7}, {"id": 116, "x": 1, "y": 8}
      ]
    },
    {
      "id": "eg",
      "name": "Erdgeschoss",
      "grid": {"columns": 7, "rows": 3},
      "tables": [
        {"id": 1, "x": 1, "y": 3}, {"id": 2, "x": 1, "y": 1}, {"id": 3, "x": 3, "y": 1},
        {"id": 4, "x": 5, "y": 1}, {"id": 5, "x": 7, "y": 1}, {"id": 6, "x": 7, "y": 3},
	{"id": 7, "x": 4, "y": 3}
      ]
    },
    {
      "id": "terrasse",
      "name": "Terrasse",
      "grid": {"columns": 7, "rows": 1},
      "tables": [
        {"id": 27, "x": 1, "y": 1}, {"id": 28, "x": 2, "y": 1}, {"id": 29, "x": 3, "y": 1},
	{"id": 20, "x": 5, "y": 1}, {"id": 21, "x": 6, "y": 1}, {"id": 22, "x": 7, "y": 1},
      ]
    }
  ]
}